alp_objectifier/__init__.py
alp_objectifier/constants.py
alp_objectifier/converter.py
alp_objectifier/exceptions.py
alp_objectifier/util.py
alp_objectifier/anylogic_types/__init__.py
alp_objectifier/anylogic_types/agent_class.py
alp_objectifier/anylogic_types/agent_objects.py
alp_objectifier/anylogic_types/analyses.py
alp_objectifier/anylogic_types/dimensions.py
alp_objectifier/anylogic_types/events.py
alp_objectifier/anylogic_types/experiments.py
alp_objectifier/anylogic_types/function.py
alp_objectifier/anylogic_types/java_class.py
alp_objectifier/anylogic_types/misc.py
alp_objectifier/anylogic_types/model.py
alp_objectifier/anylogic_types/optionlist.py
alp_objectifier/anylogic_types/presentations.py
alp_objectifier/anylogic_types/resources.py
alp_objectifier/anylogic_types/schedule.py
alp_objectifier/anylogic_types/variables.py
alp_objectifier-0.1.0.dist-info/LICENSE
alp_objectifier-0.1.0.dist-info/METADATA
alp_objectifier-0.1.0.dist-info/WHEEL
alp_objectifier-0.1.0.dist-info/top_level.txt
alp_objectifier-0.1.0.dist-info/RECORD
