Metadata-Version: 2.1
Name: alp-objectifier
Version: 0.1.0
Summary: Converts AnyLogic source files (.alp) to read-only Python objects
Home-page: UNKNOWN
Author: Tyler Wolfe-Adam
License: UNKNOWN
Platform: UNKNOWN
Classifier: Programming Language :: Python :: 3
Classifier: License :: OSI Approved :: MIT License
Classifier: Operating System :: OS Independent
Requires-Python: >=3.5
